{
"type": "FeatureCollection",
"name": "photos_origin",
"crs": { "type": "name", "properties": { "name": "urn:ogc:def:crs:OGC:1.3:CRS84" } },
"features": [
{ "type": "Feature", "properties": { "title": "Piazza Carmine, 1940-1950", "date": "1945-01-01", "labels": "piazza carmine,cotonificio,demolizione,commerci storici" }, "geometry": { "type": "Point", "coordinates": [ 14.37222674, 41.35539924 ] } },
{ "type": "Feature", "properties": { "title": "Processione dal Ponte S.Lucia, 1958", "date": "1960-01-01", "labels": "piazza carmine,convento carmine,via carmine" }, "geometry": { "type": "Point", "coordinates": [ 14.3718587, 41.35521449 ] } },
{ "type": "Feature", "properties": { "title": "Via Carmine ponte torano verso piazza Carmine circa 1900", "date": "1900-01-01", "labels": "piazza carmine,ciminera,via carmine" }, "geometry": { "type": "Point", "coordinates": [ 14.37159419, 41.35528481 ] } }
]
}
